almufti/__init__.py
almufti/cli.py
almufti/core/__init__.py
almufti/core/chat_engine.py
almufti/core/language_processor.py
almufti/database/__init__.py
almufti/database/db_manager.py
almufti/homework/__init__.py
almufti/homework/math_solver.py
almufti/learning/__init__.py
almufti/learning/continuous_learning.py
almufti/search/__init__.py
almufti/search/web_search.py
tests/__init__.py
tests/test_basic.py
almufti_bin_badran-1.0.0.dist-info/LICENSE
almufti_bin_badran-1.0.0.dist-info/METADATA
almufti_bin_badran-1.0.0.dist-info/WHEEL
almufti_bin_badran-1.0.0.dist-info/entry_points.txt
almufti_bin_badran-1.0.0.dist-info/top_level.txt
almufti_bin_badran-1.0.0.dist-info/RECORD
