Metadata-Version: 2.1
Name: almufti-bin-badran
Version: 1.0.0
Summary: A lightweight AI assistant with Arabic language support for mobile and offline use
Home-page: https://github.com/yourusername/almufti-bin-badran
Author: Almufti Development Team
Author-email: dev@almufti.ai
License: UNKNOWN
Platform: UNKNOWN
Classifier: Programming Language :: Python :: 3
Classifier: Programming Language :: Python :: 3.8
Classifier: Programming Language :: Python :: 3.9
Classifier: Programming Language :: Python :: 3.10
Classifier: Programming Language :: Python :: 3.11
Classifier: License :: OSI Approved :: MIT License
Classifier: Operating System :: OS Independent
Classifier: Intended Audience :: Developers
Classifier: Intended Audience :: Education
Classifier: Topic :: Scientific/Engineering :: Artificial Intelligence
Classifier: Topic :: Text Processing :: Linguistic
Requires-Python: >=3.8
License-File: LICENSE
Requires-Dist: beautifulsoup4 (>=4.12.0)
Requires-Dist: colorama (>=0.4.6)
Requires-Dist: duckduckgo-search (>=3.9.0)
Requires-Dist: langdetect (>=1.0.9)
Requires-Dist: lxml (>=4.9.0)
Requires-Dist: nltk (>=3.8.1)
Requires-Dist: numpy (>=1.23.0)
Requires-Dist: pandas (>=1.5.0)
Requires-Dist: pyarabic (>=0.6.15)
Requires-Dist: python-dotenv (>=1.0.0)
Requires-Dist: pyyaml (>=6.0)
Requires-Dist: requests (>=2.31.0)
Requires-Dist: spacy (>=3.5.0)
Requires-Dist: sqlalchemy (>=2.0.0)
Requires-Dist: torch (>=2.0.0)
Requires-Dist: tqdm (>=4.65.0)
Requires-Dist: transformers (>=4.30.0)
Provides-Extra: audio
Requires-Dist: librosa (>=0.10.0) ; extra == 'audio'
Requires-Dist: soundfile (>=0.12.1) ; extra == 'audio'
Provides-Extra: dev
Requires-Dist: black (>=23.0.0) ; extra == 'dev'
Requires-Dist: flake8 (>=6.0.0) ; extra == 'dev'
Requires-Dist: pytest-cov (>=4.1.0) ; extra == 'dev'
Requires-Dist: pytest (>=7.4.0) ; extra == 'dev'
